rich_logger/__init__.py
rich_logger/pl_logger.py
rich_logger/spacy_logger.py
rich_logger/table_printer.py
rich_logger-0.3.2.dist-info/licenses/LICENSE
rich_logger-0.3.2.dist-info/METADATA
rich_logger-0.3.2.dist-info/WHEEL
rich_logger-0.3.2.dist-info/entry_points.txt
rich_logger-0.3.2.dist-info/top_level.txt
rich_logger-0.3.2.dist-info/RECORD
