Metadata-Version: 2.4
Name: rich-logger
Version: 0.3.2
Summary: Table logger using Rich
Author-email: Perceval Wajsburt <perceval.wajsburt@gmail.com>
License: BSD 3-Clause License
Requires-Python: <4.0,>=3.7
License-File: LICENSE
Requires-Dist: rich>=10.11.0
Requires-Dist: pydantic>=1.0.0
Provides-Extra: dev
Requires-Dist: pytest>=7.1.3; extra == "dev"
Requires-Dist: coverage>=6.5.0; extra == "dev"
Requires-Dist: pytest-cov>=4.0.0; extra == "dev"
Requires-Dist: pre-commit>=2.20.0; extra == "dev"
Requires-Dist: tqdm>=2.0.0; extra == "dev"
Requires-Dist: pytorch-lightning>=1.0.0; extra == "dev"
Dynamic: license-file
